{"match":{"id":"558508","market_id":"558508","title":"Wimbledon: Tarvet vs. Alcaraz ","slug":"wimbledon-tarvet-vs-alcaraz","polymarket_url":"https://polymarket.com/event/wimbledon-tarvet-vs-alcaraz","date":"2025-07-02T05:52:23.745907+07:00","start_date":"2025-07-02T05:52:23.745907","end_date":"2025-07-02T07:00:00","players":["Tarvet","Alcaraz"],"volume":116595.468087,"status":"completed","price_points":6},"price_history":{"pregame":[],"ingame":[{"t":1751410808,"p":0.1},{"t":1751411407,"p":0.1},{"t":1751412008,"p":0.1},{"t":1751412608,"p":0.1},{"t":1751413207,"p":0.1},{"t":1751413807,"p":0.1}]}}