{"match":{"id":"570337","market_id":"570337","title":"ATP Toronto \u2013 Rublev vs. Sonego","slug":"atp-toronto-rublev-vs-sonego","polymarket_url":"https://polymarket.com/event/atp-toronto-rublev-vs-sonego","date":"2025-08-01T04:13:46.583771+07:00","start_date":"2025-08-01T04:13:46.583771","end_date":"2025-08-01T07:00:00","players":["Rublev","Sonego"],"volume":65828.565842,"status":"completed","price_points":16},"price_history":{"pregame":[],"ingame":[{"t":1753996809,"p":0.72},{"t":1753997410,"p":0.715},{"t":1753998010,"p":0.715},{"t":1753998610,"p":0.715},{"t":1753999209,"p":0.715},{"t":1753999810,"p":0.715},{"t":1754000409,"p":0.715},{"t":1754001008,"p":0.715},{"t":1754001609,"p":0.715},{"t":1754002209,"p":0.715},{"t":1754002809,"p":0.715},{"t":1754003409,"p":0.715},{"t":1754004010,"p":0.715},{"t":1754004609,"p":0.715},{"t":1754005210,"p":0.715},{"t":1754005810,"p":0.715}]}}